{
  "filePath": "/Users/gabriel.herter/Documents/Personal/ai-framework/vscode-extension/src/types/feedback.ts",
  "taskId": "LOCAL-014",
  "baseline": {
    "capturedAt": "2025-12-30T11:08:37.896Z",
    "hash": "e3b0c44298fc1c14",
    "size": 0
  },
  "accumulated": {
    "lastUpdatedAt": "2025-12-30T11:08:37.896Z",
    "hash": "5ee0305bc1716e6f",
    "size": 1093,
    "editCount": 1
  },
  "sync": {
    "lastCheckedAt": "2025-12-30T11:08:37.896Z",
    "actualFileHash": "5ee0305bc1716e6f",
    "status": "synced"
  }
}