{
  "id": "evt-1767057256103-d9y4zvo9d",
  "taskId": "LOCAL-009",
  "taskIdSource": "active-task-file",
  "tool": "TodoWrite",
  "input": {
    "todos": [
      {
        "content": "Change TaskItem click to open description (01)",
        "status": "pending",
        "activeForm": "Changing TaskItem click behavior"
      },
      {
        "content": "Add WorkItemNode click handler (02)",
        "status": "pending",
        "activeForm": "Adding WorkItemNode click handler"
      },
      {
        "content": "Register openWorkItem command (03)",
        "status": "pending",
        "activeForm": "Registering openWorkItem command"
      }
    ]
  },
  "response": {
    "oldTodos": [],
    "newTodos": [
      {
        "content": "Change TaskItem click to open description (01)",
        "status": "pending",
        "activeForm": "Changing TaskItem click behavior"
      },
      {
        "content": "Add WorkItemNode click handler (02)",
        "status": "pending",
        "activeForm": "Adding WorkItemNode click handler"
      },
      {
        "content": "Register openWorkItem command (03)",
        "status": "pending",
        "activeForm": "Registering openWorkItem command"
      }
    ]
  },
  "sessionId": "d6d9c4c7-40e8-4c40-abc5-5fbdd91f52ce",
  "timestamp": "2025-12-30T01:14:16.103Z"
}