{
  "id": "evt-1767062434645-sqj3e5kdl",
  "taskId": "LOCAL-012",
  "taskIdSource": "active-task-file",
  "tool": "Write",
  "input": {
    "file_path": "/Users/gabriel.herter/Documents/Personal/ai-framework/.ai/tasks/todo/LOCAL-013/todo/03-vscode-feedback-button.md",
    "content": "<!--\nв•”в•ђв•ђв•ђв•ђв•ђв•ђв•ђв•ђв•ђв•ђв•ђв•ђв•ђв•ђв•ђв•ђв•ђв•ђв•ђв•ђв•ђв•ђв•ђв•ђв•ђв•ђв•ђв•ђв•ђв•ђв•ђв•ђв•ђв•ђв•ђв•ђв•ђв•ђв•ђв•ђв•ђв•ђв•ђв•ђв•ђв•ђв•ђв•ђв•ђв•ђв•ђв•ђв•ђв•ђв•ђв•ђв•ђв•ђв•ђв•ђв•ђв•ђв•ђв•ђв•ђв•ђв•—\nв•‘ WORK ITEM: 03-vscode-feedback-button.md                          в•‘\nв•‘ TASK: LOCAL-013                                                  в•‘\nв• в•ђв•ђв•ђв•ђв•ђв•ђв•ђв•ђв•ђв•ђв•ђв•ђв•ђв•ђв•ђв•ђв•ђв•ђв•ђв•ђв•ђв•ђв•ђв•ђв•ђв•ђв•ђв•ђв•ђв•ђв•ђв•ђв•ђв•ђв•ђв•ђв•ђв•ђв•ђв•ђв•ђв•ђв•ђв•ђв•ђв•ђв•ђв•ђв•ђв•ђв•ђв•ђв•ђв•ђв•ђв•ђв•ђв•ђв•ђв•ђв•ђв•ђв•ђв•ђв•ђв•ђв•Ј\nв•‘ WORKFLOW:                                                        в•‘\nв•‘ 1. Move this file to in_progress/ when starting                  в•‘\nв•‘ 2. Update status.yaml with new status                            в•‘\nв•‘ 3. Complete ALL steps below                                      в•‘\nв•‘ 4. Move to done/ when complete, update status.yaml               в•‘\nв•‘ 5. Update task README with any learnings                         в•‘\nв•љв•ђв•ђв•ђв•ђв•ђв•ђв•ђв•ђв•ђв•ђв•ђв•ђв•ђв•ђв•ђв•ђв•ђв•ђв•ђв•ђв•ђв•ђв•ђв•ђв•ђв•ђв•ђв•ђв•ђв•ђв•ђв•ђв•ђв•ђв•ђв•ђв•ђв•ђв•ђв•ђв•ђв•ђв•ђв•ђв•ђв•ђв•ђв•ђв•ђв•ђв•ђв•ђв•ђв•ђв•ђв•ђв•ђв•ђв•ђв•ђв•ђв•ђв•ђв•ђв•ђв•ђв•ќ\n-->\n\n---\nrepo: vscode-extension\n---\n\n# VSCode Feedback Button\n\n## Objective\n\nAdd a button/action in the VSCode task panel that opens the feedback file for the selected task, making it easy for users to add review comments.\n\n## Implementation Steps\n\n### Step 1: Add tree item action\n\n**File**: `vscode-extension/src/providers/TaskTreeProvider.ts`\n\nAdd an inline action button to task items:\n\n```typescript\n// In TaskItem class or when creating tree items\ncontextValue = 'task';  // Already exists\n\n// Add inline button via package.json menus\n```\n\n### Step 2: Register command\n\n**File**: `vscode-extension/src/extension.ts`\n\n```typescript\nconst openFeedbackFile = vscode.commands.registerCommand(\n  'aiCockpit.openFeedbackFile',\n  async (item: { taskId: string; taskPath: string }) => {\n    const feedbackPath = path.join(\n      item.taskPath,\n      'feedback',\n      'diff-review.md'\n    );\n\n    // Create file from template if it doesn't exist\n    if (!fs.existsSync(feedbackPath)) {\n      const templatePath = path.join(\n        workspaceRoot,\n        '.ai/_framework/templates/feedback-template.md'\n      );\n\n      if (fs.existsSync(templatePath)) {\n        fs.mkdirSync(path.dirname(feedbackPath), { recursive: true });\n        fs.copyFileSync(templatePath, feedbackPath);\n      } else {\n        // Create minimal file\n        fs.writeFileSync(feedbackPath, '# Diff Feedback\\n\\nAdd your feedback below.\\n');\n      }\n    }\n\n    // Open in editor\n    const doc = await vscode.workspace.openTextDocument(feedbackPath);\n    await vscode.window.showTextDocument(doc);\n  }\n);\n```\n\n### Step 3: Add menu contribution\n\n**File**: `vscode-extension/package.json`\n\n```json\n{\n  \"contributes\": {\n    \"menus\": {\n      \"view/item/context\": [\n        {\n          \"command\": \"aiCockpit.openFeedbackFile\",\n          \"when\": \"view == aiCockpit.tasks && viewItem == task\",\n          \"group\": \"inline\"\n        }\n      ]\n    },\n    \"commands\": [\n      {\n        \"command\": \"aiCockpit.openFeedbackFile\",\n        \"title\": \"Open Feedback\",\n        \"icon\": \"$(comment-discussion)\"\n      }\n    ]\n  }\n}\n```\n\n### Step 4: Show feedback indicator\n\nOptionally show a badge or indicator when feedback file has unresolved items:\n\n```typescript\n// In TaskTreeProvider, when creating TaskItem\nconst hasFeedback = await this.checkForFeedback(taskPath);\nif (hasFeedback) {\n  item.description = `${item.description} рџ’¬`;\n}\n```\n\n## Acceptance Criteria\n\n- [ ] Command registered: `aiCockpit.openFeedbackFile`\n- [ ] Button visible on task items in tree view\n- [ ] Clicking opens feedback file in editor\n- [ ] Creates file from template if doesn't exist\n- [ ] (Optional) Shows indicator when feedback exists\n\n## Testing\n\n1. Click feedback button on a task\n2. Verify file opens (or is created then opens)\n3. Add some feedback, save\n4. Verify file persists\n5. Test with task that has no feedback folder\n\n## Notes\n\n- Use comment-discussion icon for the button\n- Consider adding keyboard shortcut\n- File should open in current editor group\n"
  },
  "response": {
    "type": "create",
    "filePath": "/Users/gabriel.herter/Documents/Personal/ai-framework/.ai/tasks/todo/LOCAL-013/todo/03-vscode-feedback-button.md",
    "content": "<!--\nв•”в•ђв•ђв•ђв•ђв•ђв•ђв•ђв•ђв•ђв•ђв•ђв•ђв•ђв•ђв•ђв•ђв•ђв•ђв•ђв•ђв•ђв•ђв•ђв•ђв•ђв•ђв•ђв•ђв•ђв•ђв•ђв•ђв•ђв•ђв•ђв•ђв•ђв•ђв•ђв•ђв•ђв•ђв•ђв•ђв•ђв•ђв•ђв•ђв•ђв•ђв•ђв•ђв•ђв•ђв•ђв•ђв•ђв•ђв•ђв•ђв•ђв•ђв•ђв•ђв•ђв•ђв•—\nв•‘ WORK ITEM: 03-vscode-feedback-button.md                          в•‘\nв•‘ TASK: LOCAL-013                                                  в•‘\nв• в•ђв•ђв•ђв•ђв•ђв•ђв•ђв•ђв•ђв•ђв•ђв•ђв•ђв•ђв•ђв•ђв•ђв•ђв•ђв•ђв•ђв•ђв•ђв•ђв•ђв•ђв•ђв•ђв•ђв•ђв•ђв•ђв•ђв•ђв•ђв•ђв•ђв•ђв•ђв•ђв•ђв•ђв•ђв•ђв•ђв•ђв•ђв•ђв•ђв•ђв•ђв•ђв•ђв•ђв•ђв•ђв•ђв•ђв•ђв•ђв•ђв•ђв•ђв•ђв•ђв•ђв•Ј\nв•‘ WORKFLOW:                                                        в•‘\nв•‘ 1. Move this file to in_progress/ when starting                  в•‘\nв•‘ 2. Update status.yaml with new status                            в•‘\nв•‘ 3. Complete ALL steps below                                      в•‘\nв•‘ 4. Move to done/ when complete, update status.yaml               в•‘\nв•‘ 5. Update task README with any learnings                         в•‘\nв•љв•ђв•ђв•ђв•ђв•ђв•ђв•ђв•ђв•ђв•ђв•ђв•ђв•ђв•ђв•ђв•ђв•ђв•ђв•ђв•ђв•ђв•ђв•ђв•ђв•ђв•ђв•ђв•ђв•ђв•ђв•ђв•ђв•ђв•ђв•ђв•ђв•ђв•ђв•ђв•ђв•ђв•ђв•ђв•ђв•ђв•ђв•ђв•ђв•ђв•ђв•ђв•ђв•ђв•ђв•ђв•ђв•ђв•ђв•ђв•ђв•ђв•ђв•ђв•ђв•ђв•ђв•ќ\n-->\n\n---\nrepo: vscode-extension\n---\n\n# VSCode Feedback Button\n\n## Objective\n\nAdd a button/action in the VSCode task panel that opens the feedback file for the selected task, making it easy for users to add review comments.\n\n## Implementation Steps\n\n### Step 1: Add tree item action\n\n**File**: `vscode-extension/src/providers/TaskTreeProvider.ts`\n\nAdd an inline action button to task items:\n\n```typescript\n// In TaskItem class or when creating tree items\ncontextValue = 'task';  // Already exists\n\n// Add inline button via package.json menus\n```\n\n### Step 2: Register command\n\n**File**: `vscode-extension/src/extension.ts`\n\n```typescript\nconst openFeedbackFile = vscode.commands.registerCommand(\n  'aiCockpit.openFeedbackFile',\n  async (item: { taskId: string; taskPath: string }) => {\n    const feedbackPath = path.join(\n      item.taskPath,\n      'feedback',\n      'diff-review.md'\n    );\n\n    // Create file from template if it doesn't exist\n    if (!fs.existsSync(feedbackPath)) {\n      const templatePath = path.join(\n        workspaceRoot,\n        '.ai/_framework/templates/feedback-template.md'\n      );\n\n      if (fs.existsSync(templatePath)) {\n        fs.mkdirSync(path.dirname(feedbackPath), { recursive: true });\n        fs.copyFileSync(templatePath, feedbackPath);\n      } else {\n        // Create minimal file\n        fs.writeFileSync(feedbackPath, '# Diff Feedback\\n\\nAdd your feedback below.\\n');\n      }\n    }\n\n    // Open in editor\n    const doc = await vscode.workspace.openTextDocument(feedbackPath);\n    await vscode.window.showTextDocument(doc);\n  }\n);\n```\n\n### Step 3: Add menu contribution\n\n**File**: `vscode-extension/package.json`\n\n```json\n{\n  \"contributes\": {\n    \"menus\": {\n      \"view/item/context\": [\n        {\n          \"command\": \"aiCockpit.openFeedbackFile\",\n          \"when\": \"view == aiCockpit.tasks && viewItem == task\",\n          \"group\": \"inline\"\n        }\n      ]\n    },\n    \"commands\": [\n      {\n        \"command\": \"aiCockpit.openFeedbackFile\",\n        \"title\": \"Open Feedback\",\n        \"icon\": \"$(comment-discussion)\"\n      }\n    ]\n  }\n}\n```\n\n### Step 4: Show feedback indicator\n\nOptionally show a badge or indicator when feedback file has unresolved items:\n\n```typescript\n// In TaskTreeProvider, when creating TaskItem\nconst hasFeedback = await this.checkForFeedback(taskPath);\nif (hasFeedback) {\n  item.description = `${item.description} рџ’¬`;\n}\n```\n\n## Acceptance Criteria\n\n- [ ] Command registered: `aiCockpit.openFeedbackFile`\n- [ ] Button visible on task items in tree view\n- [ ] Clicking opens feedback file in editor\n- [ ] Creates file from template if doesn't exist\n- [ ] (Optional) Shows indicator when feedback exists\n\n## Testing\n\n1. Click feedback button on a task\n2. Verify file opens (or is created then opens)\n3. Add some feedback, save\n4. Verify file persists\n5. Test with task that has no feedback folder\n\n## Notes\n\n- Use comment-discussion icon for the button\n- Consider adding keyboard shortcut\n- File should open in current editor group\n",
    "structuredPatch": [],
    "originalFile": null
  },
  "sessionId": "3764ab9c-088d-4e71-9b80-408a356de620",
  "timestamp": "2025-12-30T02:40:34.645Z"
}