{
  "id": "evt-1767898756349-6nhcd6g15",
  "taskId": "EEXPR-12",
  "taskIdSource": "active-task-file",
  "tool": "Write",
  "input": {
    "file_path": "/Users/gabriel.herter/Documents/Projects/deel/.ai/tasks/todo/EEXPR-12-3/todo/03-create-enrichment-service.md",
    "content": "<!--\n╔══════════════════════════════════════════════════════════════════╗\n║ WORK ITEM: 03-create-enrichment-service.md                       ║\n║ TASK: EEXPR-12-3                                                 ║\n╚══════════════════════════════════════════════════════════════════╝\n-->\n\n---\nrepo: backend\n---\n\n# Create Enrichment Service: TransferEnrichmentService\n\n## Objective\n\nCreate a service to enrich raw transfer data with profile, email, and legal entity information from backend's database.\n\n## Implementation Steps\n\n### Step 1: Create service file\n\n**File:** `backend/services/peo/entity_transfer/helpers/transfer_enrichment_service.ts` (NEW)\n\n```typescript\nimport { Op } from 'sequelize';\nimport db from '../../../../models';\n\nconst { Profile, Contract, LegalEntity } = db;\n\ninterface LegalEntityInfo {\n  publicId: string;\n  legalName: string;\n  countryCode: string | null;\n}\n\ninterface ProfileInfo {\n  publicId: string;\n  name: string;\n  email: string;\n  jobTitle: string | null;\n}\n\nexport class TransferEnrichmentService {\n  /**\n   * Batch fetch legal entities by publicIds\n   */\n  async fetchLegalEntities(publicIds: string[]): Promise<Map<string, LegalEntityInfo>> {\n    if (publicIds.length === 0) return new Map();\n\n    const entities = await LegalEntity.findAll({\n      where: { publicId: { [Op.in]: publicIds } },\n      attributes: ['publicId', 'name', 'address'],\n      useMaster: false,\n    });\n\n    return new Map(\n      entities.map((e) => [\n        e.publicId,\n        {\n          publicId: e.publicId,\n          legalName: e.name,\n          countryCode: e.address?.country || null,\n        },\n      ])\n    );\n  }\n\n  /**\n   * Batch fetch emails for contracts via Contract → Profile join\n   */\n  async fetchContractEmails(contractIds: number[]): Promise<Map<number, string | null>> {\n    if (contractIds.length === 0) return new Map();\n\n    const contracts = await Contract.findAll({\n      where: { id: { [Op.in]: contractIds } },\n      include: [\n        {\n          model: Profile,\n          as: 'Contractor',\n          attributes: ['email'],\n          required: false,\n        },\n      ],\n      attributes: ['id'],\n      useMaster: false,\n    });\n\n    return new Map(contracts.map((c) => [c.id, c.Contractor?.email || null]));\n  }\n\n  /**\n   * Batch fetch profiles by publicIds\n   */\n  async fetchProfiles(publicIds: string[]): Promise<Map<string, ProfileInfo>> {\n    if (publicIds.length === 0) return new Map();\n\n    const profiles = await Profile.findAll({\n      where: { publicId: { [Op.in]: publicIds } },\n      attributes: ['publicId', 'firstName', 'lastName', 'email', 'jobTitle'],\n      useMaster: false,\n    });\n\n    return new Map(\n      profiles.map((p) => [\n        p.publicId,\n        {\n          publicId: p.publicId,\n          name: `${p.firstName} ${p.lastName}`.trim(),\n          email: p.email,\n          jobTitle: p.jobTitle || null,\n        },\n      ])\n    );\n  }\n\n  /**\n   * Enrich raw transfers with profile, email, and legal entity data\n   */\n  async enrichTransfers(rawTransfers: RawTransfer[]): Promise<EnrichedTransfer[]> {\n    // 1. Collect all IDs for batch fetching\n    const legalEntityIds = new Set<string>();\n    const contractIds = new Set<number>();\n    const profilePublicIds = new Set<string>();\n\n    for (const transfer of rawTransfers) {\n      legalEntityIds.add(transfer.sourceLegalEntityPublicId);\n      legalEntityIds.add(transfer.destinationLegalEntityPublicId);\n\n      for (const item of transfer.items) {\n        if (item.deelContractId) {\n          contractIds.add(item.deelContractId);\n        }\n      }\n\n      for (const signature of transfer.signatures) {\n        profilePublicIds.add(signature.profilePublicId);\n      }\n    }\n\n    // 2. Batch fetch all enrichment data in parallel\n    const [legalEntityMap, contractEmailMap, profileMap] = await Promise.all([\n      this.fetchLegalEntities(Array.from(legalEntityIds)),\n      this.fetchContractEmails(Array.from(contractIds)),\n      this.fetchProfiles(Array.from(profilePublicIds)),\n    ]);\n\n    // 3. Enrich transfers with O(1) lookups\n    return rawTransfers.map((transfer) => ({\n      id: transfer.id,\n      status: transfer.status,\n      organizationId: transfer.organizationId,\n      requesterPublicProfileId: transfer.requesterProfilePublicId,\n      sourceLegalEntity: legalEntityMap.get(transfer.sourceLegalEntityPublicId) || {\n        publicId: transfer.sourceLegalEntityPublicId,\n        legalName: null,\n        countryCode: null,\n      },\n      destinationLegalEntity: legalEntityMap.get(transfer.destinationLegalEntityPublicId) || {\n        publicId: transfer.destinationLegalEntityPublicId,\n        legalName: null,\n        countryCode: null,\n      },\n      effectiveDate: transfer.effectiveDate,\n      items: transfer.items.map((item) => ({\n        id: item.id,\n        peoContractOid: item.baseContractOid,\n        employeeName: item.employeeName,\n        employeeEmail: item.deelContractId\n          ? contractEmailMap.get(item.deelContractId) || null\n          : null,\n        status: item.status,\n        benefitGroupId: item.benefitGroupId,\n        payGroupId: item.payGroupId,\n        ptoPolicyId: item.ptoPolicyId,\n        workLocationId: item.workLocationId,\n        positionPublicId: item.positionPublicId,\n        teamId: item.teamId,\n        newContractOid: item.newContractOid,\n        resumeFromStep: item.resumeFromStep,\n      })),\n      signatures: this.groupSignaturesByRole(transfer.signatures, profileMap),\n      agreementId: transfer.agreement?.id || null,\n      agreement: transfer.agreement\n        ? {\n            id: transfer.agreement.id,\n            pdfUrl: transfer.agreement.pdfUrl,\n            type: transfer.agreement.type,\n            createdAt: transfer.agreement.createdAt,\n            expiresAt: null,\n          }\n        : null,\n      createdAt: transfer.createdAt,\n      updatedAt: transfer.updatedAt,\n    }));\n  }\n\n  /**\n   * Group signatures by role and enrich with profile data\n   */\n  private groupSignaturesByRole(\n    signatures: RawTransferSignature[],\n    profileMap: Map<string, ProfileInfo>\n  ): { admins: EnrichedSignature[]; employees: EnrichedSignature[] } {\n    const admins: EnrichedSignature[] = [];\n    const employees: EnrichedSignature[] = [];\n\n    for (const sig of signatures) {\n      const profile = profileMap.get(sig.profilePublicId);\n      const enrichedSig: EnrichedSignature = {\n        publicProfileId: sig.profilePublicId,\n        name: profile?.name || null,\n        email: profile?.email || null,\n        jobTitle: profile?.jobTitle || null,\n        role: sig.role,\n        agreementType: sig.agreementType,\n        status: sig.signedAt ? 'SIGNED' : 'AWAITING_SIGNATURE',\n        signedAt: sig.signedAt,\n      };\n\n      if (sig.role === 'ADMIN') {\n        admins.push(enrichedSig);\n      } else {\n        employees.push(enrichedSig);\n      }\n    }\n\n    return { admins, employees };\n  }\n}\n\nexport const transferEnrichmentService = new TransferEnrichmentService();\n```\n\n### Step 2: Add type exports\n\nAdd types at the top of the file or in a separate types file:\n\n```typescript\ninterface RawTransfer {\n  id: string;\n  status: string;\n  organizationId: number;\n  requesterProfilePublicId: string;\n  sourceLegalEntityPublicId: string;\n  destinationLegalEntityPublicId: string;\n  effectiveDate: string;\n  items: RawTransferItem[];\n  signatures: RawTransferSignature[];\n  agreement: RawTransferAgreement | null;\n  createdAt: string;\n  updatedAt: string;\n}\n\ninterface EnrichedTransfer {\n  id: string;\n  status: string;\n  organizationId: number;\n  requesterPublicProfileId: string;\n  sourceLegalEntity: LegalEntityInfo;\n  destinationLegalEntity: LegalEntityInfo;\n  effectiveDate: string;\n  items: EnrichedItem[];\n  signatures: { admins: EnrichedSignature[]; employees: EnrichedSignature[] };\n  agreementId: string | null;\n  agreement: EnrichedAgreement | null;\n  createdAt: string;\n  updatedAt: string;\n}\n\ninterface EnrichedSignature {\n  publicProfileId: string;\n  name: string | null;\n  email: string | null;\n  jobTitle: string | null;\n  role: string;\n  agreementType: string;\n  status: string;\n  signedAt: string | null;\n}\n```\n\n## Key Files\n\n| File | Purpose |\n|------|---------|\n| `backend/services/peo/entity_transfer/helpers/transfer_enrichment_service.ts` | Enrichment service |\n| `backend/models/profile.js` | Profile model |\n| `backend/models/contract.js` | Contract model |\n| `backend/models/legal_entity.js` | Legal entity model |\n\n## Acceptance Criteria\n\n- [ ] `fetchLegalEntities()` batch fetches legal entities\n- [ ] `fetchContractEmails()` batch fetches emails via Contract → Profile\n- [ ] `fetchProfiles()` batch fetches profile data\n- [ ] `enrichTransfers()` orchestrates all enrichment\n- [ ] All methods use `Op.in` pattern (no N+1)\n- [ ] All methods use `useMaster: false` for read replica\n- [ ] Signatures grouped by role (admins/employees)\n"
  },
  "response": {
    "type": "create",
    "filePath": "/Users/gabriel.herter/Documents/Projects/deel/.ai/tasks/todo/EEXPR-12-3/todo/03-create-enrichment-service.md",
    "content": "<!--\n╔══════════════════════════════════════════════════════════════════╗\n║ WORK ITEM: 03-create-enrichment-service.md                       ║\n║ TASK: EEXPR-12-3                                                 ║\n╚══════════════════════════════════════════════════════════════════╝\n-->\n\n---\nrepo: backend\n---\n\n# Create Enrichment Service: TransferEnrichmentService\n\n## Objective\n\nCreate a service to enrich raw transfer data with profile, email, and legal entity information from backend's database.\n\n## Implementation Steps\n\n### Step 1: Create service file\n\n**File:** `backend/services/peo/entity_transfer/helpers/transfer_enrichment_service.ts` (NEW)\n\n```typescript\nimport { Op } from 'sequelize';\nimport db from '../../../../models';\n\nconst { Profile, Contract, LegalEntity } = db;\n\ninterface LegalEntityInfo {\n  publicId: string;\n  legalName: string;\n  countryCode: string | null;\n}\n\ninterface ProfileInfo {\n  publicId: string;\n  name: string;\n  email: string;\n  jobTitle: string | null;\n}\n\nexport class TransferEnrichmentService {\n  /**\n   * Batch fetch legal entities by publicIds\n   */\n  async fetchLegalEntities(publicIds: string[]): Promise<Map<string, LegalEntityInfo>> {\n    if (publicIds.length === 0) return new Map();\n\n    const entities = await LegalEntity.findAll({\n      where: { publicId: { [Op.in]: publicIds } },\n      attributes: ['publicId', 'name', 'address'],\n      useMaster: false,\n    });\n\n    return new Map(\n      entities.map((e) => [\n        e.publicId,\n        {\n          publicId: e.publicId,\n          legalName: e.name,\n          countryCode: e.address?.country || null,\n        },\n      ])\n    );\n  }\n\n  /**\n   * Batch fetch emails for contracts via Contract → Profile join\n   */\n  async fetchContractEmails(contractIds: number[]): Promise<Map<number, string | null>> {\n    if (contractIds.length === 0) return new Map();\n\n    const contracts = await Contract.findAll({\n      where: { id: { [Op.in]: contractIds } },\n      include: [\n        {\n          model: Profile,\n          as: 'Contractor',\n          attributes: ['email'],\n          required: false,\n        },\n      ],\n      attributes: ['id'],\n      useMaster: false,\n    });\n\n    return new Map(contracts.map((c) => [c.id, c.Contractor?.email || null]));\n  }\n\n  /**\n   * Batch fetch profiles by publicIds\n   */\n  async fetchProfiles(publicIds: string[]): Promise<Map<string, ProfileInfo>> {\n    if (publicIds.length === 0) return new Map();\n\n    const profiles = await Profile.findAll({\n      where: { publicId: { [Op.in]: publicIds } },\n      attributes: ['publicId', 'firstName', 'lastName', 'email', 'jobTitle'],\n      useMaster: false,\n    });\n\n    return new Map(\n      profiles.map((p) => [\n        p.publicId,\n        {\n          publicId: p.publicId,\n          name: `${p.firstName} ${p.lastName}`.trim(),\n          email: p.email,\n          jobTitle: p.jobTitle || null,\n        },\n      ])\n    );\n  }\n\n  /**\n   * Enrich raw transfers with profile, email, and legal entity data\n   */\n  async enrichTransfers(rawTransfers: RawTransfer[]): Promise<EnrichedTransfer[]> {\n    // 1. Collect all IDs for batch fetching\n    const legalEntityIds = new Set<string>();\n    const contractIds = new Set<number>();\n    const profilePublicIds = new Set<string>();\n\n    for (const transfer of rawTransfers) {\n      legalEntityIds.add(transfer.sourceLegalEntityPublicId);\n      legalEntityIds.add(transfer.destinationLegalEntityPublicId);\n\n      for (const item of transfer.items) {\n        if (item.deelContractId) {\n          contractIds.add(item.deelContractId);\n        }\n      }\n\n      for (const signature of transfer.signatures) {\n        profilePublicIds.add(signature.profilePublicId);\n      }\n    }\n\n    // 2. Batch fetch all enrichment data in parallel\n    const [legalEntityMap, contractEmailMap, profileMap] = await Promise.all([\n      this.fetchLegalEntities(Array.from(legalEntityIds)),\n      this.fetchContractEmails(Array.from(contractIds)),\n      this.fetchProfiles(Array.from(profilePublicIds)),\n    ]);\n\n    // 3. Enrich transfers with O(1) lookups\n    return rawTransfers.map((transfer) => ({\n      id: transfer.id,\n      status: transfer.status,\n      organizationId: transfer.organizationId,\n      requesterPublicProfileId: transfer.requesterProfilePublicId,\n      sourceLegalEntity: legalEntityMap.get(transfer.sourceLegalEntityPublicId) || {\n        publicId: transfer.sourceLegalEntityPublicId,\n        legalName: null,\n        countryCode: null,\n      },\n      destinationLegalEntity: legalEntityMap.get(transfer.destinationLegalEntityPublicId) || {\n        publicId: transfer.destinationLegalEntityPublicId,\n        legalName: null,\n        countryCode: null,\n      },\n      effectiveDate: transfer.effectiveDate,\n      items: transfer.items.map((item) => ({\n        id: item.id,\n        peoContractOid: item.baseContractOid,\n        employeeName: item.employeeName,\n        employeeEmail: item.deelContractId\n          ? contractEmailMap.get(item.deelContractId) || null\n          : null,\n        status: item.status,\n        benefitGroupId: item.benefitGroupId,\n        payGroupId: item.payGroupId,\n        ptoPolicyId: item.ptoPolicyId,\n        workLocationId: item.workLocationId,\n        positionPublicId: item.positionPublicId,\n        teamId: item.teamId,\n        newContractOid: item.newContractOid,\n        resumeFromStep: item.resumeFromStep,\n      })),\n      signatures: this.groupSignaturesByRole(transfer.signatures, profileMap),\n      agreementId: transfer.agreement?.id || null,\n      agreement: transfer.agreement\n        ? {\n            id: transfer.agreement.id,\n            pdfUrl: transfer.agreement.pdfUrl,\n            type: transfer.agreement.type,\n            createdAt: transfer.agreement.createdAt,\n            expiresAt: null,\n          }\n        : null,\n      createdAt: transfer.createdAt,\n      updatedAt: transfer.updatedAt,\n    }));\n  }\n\n  /**\n   * Group signatures by role and enrich with profile data\n   */\n  private groupSignaturesByRole(\n    signatures: RawTransferSignature[],\n    profileMap: Map<string, ProfileInfo>\n  ): { admins: EnrichedSignature[]; employees: EnrichedSignature[] } {\n    const admins: EnrichedSignature[] = [];\n    const employees: EnrichedSignature[] = [];\n\n    for (const sig of signatures) {\n      const profile = profileMap.get(sig.profilePublicId);\n      const enrichedSig: EnrichedSignature = {\n        publicProfileId: sig.profilePublicId,\n        name: profile?.name || null,\n        email: profile?.email || null,\n        jobTitle: profile?.jobTitle || null,\n        role: sig.role,\n        agreementType: sig.agreementType,\n        status: sig.signedAt ? 'SIGNED' : 'AWAITING_SIGNATURE',\n        signedAt: sig.signedAt,\n      };\n\n      if (sig.role === 'ADMIN') {\n        admins.push(enrichedSig);\n      } else {\n        employees.push(enrichedSig);\n      }\n    }\n\n    return { admins, employees };\n  }\n}\n\nexport const transferEnrichmentService = new TransferEnrichmentService();\n```\n\n### Step 2: Add type exports\n\nAdd types at the top of the file or in a separate types file:\n\n```typescript\ninterface RawTransfer {\n  id: string;\n  status: string;\n  organizationId: number;\n  requesterProfilePublicId: string;\n  sourceLegalEntityPublicId: string;\n  destinationLegalEntityPublicId: string;\n  effectiveDate: string;\n  items: RawTransferItem[];\n  signatures: RawTransferSignature[];\n  agreement: RawTransferAgreement | null;\n  createdAt: string;\n  updatedAt: string;\n}\n\ninterface EnrichedTransfer {\n  id: string;\n  status: string;\n  organizationId: number;\n  requesterPublicProfileId: string;\n  sourceLegalEntity: LegalEntityInfo;\n  destinationLegalEntity: LegalEntityInfo;\n  effectiveDate: string;\n  items: EnrichedItem[];\n  signatures: { admins: EnrichedSignature[]; employees: EnrichedSignature[] };\n  agreementId: string | null;\n  agreement: EnrichedAgreement | null;\n  createdAt: string;\n  updatedAt: string;\n}\n\ninterface EnrichedSignature {\n  publicProfileId: string;\n  name: string | null;\n  email: string | null;\n  jobTitle: string | null;\n  role: string;\n  agreementType: string;\n  status: string;\n  signedAt: string | null;\n}\n```\n\n## Key Files\n\n| File | Purpose |\n|------|---------|\n| `backend/services/peo/entity_transfer/helpers/transfer_enrichment_service.ts` | Enrichment service |\n| `backend/models/profile.js` | Profile model |\n| `backend/models/contract.js` | Contract model |\n| `backend/models/legal_entity.js` | Legal entity model |\n\n## Acceptance Criteria\n\n- [ ] `fetchLegalEntities()` batch fetches legal entities\n- [ ] `fetchContractEmails()` batch fetches emails via Contract → Profile\n- [ ] `fetchProfiles()` batch fetches profile data\n- [ ] `enrichTransfers()` orchestrates all enrichment\n- [ ] All methods use `Op.in` pattern (no N+1)\n- [ ] All methods use `useMaster: false` for read replica\n- [ ] Signatures grouped by role (admins/employees)\n",
    "structuredPatch": [],
    "originalFile": null
  },
  "sessionId": "dd73030c-1dff-4bc1-a371-2f1717e04e8f",
  "timestamp": "2026-01-08T18:59:16.349Z"
}